setup.cfg
setup.py
SchevoWeb.egg-info/PKG-INFO
SchevoWeb.egg-info/SOURCES.txt
SchevoWeb.egg-info/dependency_links.txt
SchevoWeb.egg-info/entry_points.txt
SchevoWeb.egg-info/not-zip-safe
SchevoWeb.egg-info/requires.txt
SchevoWeb.egg-info/top_level.txt
schevoweb/__init__.py
schevoweb/helper.py
schevoweb/form/__init__.py
schevoweb/form/fill.py
schevoweb/form/template.py
schevoweb/form/update.py
