Metadata-Version: 1.0
Name: SchevoWeb
Version: 1.0a2
Summary: Schevo tools for web development
Home-page: http://schevo.org/trac/wiki/SchevoWeb
Author: Orbtech, L.L.C. and contributors
Author-email: schevo-devel@lists.schevo.org
License: LGPL
Platform: UNIX
Platform: Windows
Classifier: Development Status :: 3 - Alpha
Classifier: Environment :: Console
Classifier: Intended Audience :: Developers
Classifier: License :: OSI Approved :: GNU Library or Lesser General Public License (LGPL)
Classifier: Operating System :: OS Independent
Classifier: Programming Language :: Python
Classifier: Topic :: Database :: Database Engines/Servers
Classifier: Topic :: Software Development :: Libraries :: Application Frameworks
